{"date": "25-08-27_15:36", "corpus": "longest", "method": "vector_database", "model": "LaBSE", "fuzziness": 0.3, "comments": "LaBSE-Modell mit Stopwörtern", "results": [["E000036", 1660, "Predigt,Paragraph,Satz,Liedvers,Liederbuch,Ähnlichkeit,Validated,Dopplung\n12,nichts auf der erden,23,33,nichts findet sich ja auf der erden,827,0.1833297312259674,False,False\n14,jst voller freud und singen,24,1,ift voller freud und singen,903,0.24652299284934998,True,False\n19,das was mich singend machet,24,4,das was mich singen machet,903,0.04442167282104492,True,False\n20,jst was im himmel ist,24,5,ist was im himmel ist,903,0.11600646376609802,True,False\n24,du giebest mir allein,29,4,du hilffst mir allein,929,0.1772790253162384,False,True\n27,zwingt die säiten in cithara,30,0,zwingt die sensen in cythara,741,0.2770376205444336,True,False\n28,und laßt die süsse musica gantz freudenreich erschallen,30,1,und lafst die süss se musica gank frendenreich erschallen,741,0.22514912486076355,True,True\n29,daß ich möge mit jesulein,30,2,daß ich mi ge mit jejulein,741,0.20917770266532898,True,True\n30,dem wunderschönen bräutgam mein,30,3,dem wunderschönen bräutgam nrein,741,0.287323534488678,True,True\n31,singet springet jubiliret triumphiret,30,5,singer springet jubiliret triumphiret,741,0.19591876864433289,True,True\n32,danckt dem herren groß ist der könig der ehren,30,6,danckt dem herren groß ist der könig der ehren,741,2.5965866826474504e-13,True,True\n36,gebt unserm gott die ehre,32,1,gebt unserm gott die ehre,1111,2.8752521197272785e-13,True,True\n37,jhr die ihr gottes macht bekennt,32,2,jhr die ihr gottes macht bekennt,1111,6.744338160863395e-13,True,True\n40,gebt unserm gott die ehre,32,3,gebt unserm gott die ehre,1111,2.8752521197272785e-13,True,True\n42,die falschen götzen macht zu spott,32,4,die falsche gdken macht zu spott,1111,0.18014337122440338,True,True\n43,der herr ist gott,32,5,der herr ist gut,669,0.037212878465652466,True,True\n44,der herr ist gott,32,6,der herr ist gut,669,0.037212878465652466,True,True\n46,gebt unserm gott die ehre,32,7,gebt unserm gott die ehre,1111,2.8752521197272785e-13,False,True\n77,mit singen und spielen,72,21,mit singen und mit baten,452,0.19658929109573364,False,False\n81,nun freut euch lieben christen gemein,73,0,mel nun freut euch lieben christen gmein,323,0.16596078872680664,False,True\n84,was gott an uns gewendet hat,73,4,was gott an uns gewendet hat,358,1.917631092980543e-13,True,True\n87,gar theur hat ers erworben,73,6,gar theur hat ers erworben,358,8.239028491570377e-14,True,True\n88,singet springet jubiliret triumphiret,75,0,singer springet jubiliret triumphiret,741,0.19591876864433289,False,True\n89,danckt dem herren groß ist der könig der ehren,75,1,danckt dem herren groß ist der könig der ehren,741,2.5965866826474504e-13,False,True\n110,mit harfen und mit cimbeln schon,123,1,mit harffen und mit cymbeln schon,1119,0.10735171288251877,True,True\n111,von zwölf perlen sind die pforten an der stadt,123,2,von zwölf perlen sind die pforten in deiner stadt,1119,0.14857009053230286,True,True\n112,kein aug’ hat je gespühret,123,5,kein aug hat je gespürt,1119,0.12469515204429626,True,True\n115,wenn ich in nöthen bet und sing,129,0,wann ich in ndthen bat und sing,864,0.08327163755893707,False,True\n122,mein sünd mich werden kräncken sehr,133,0,mein sund mich werden kränken sehr,997,0.12799376249313354,True,True\n123,mein gewissen wird mich nagen,133,1,mein gwissen wird mich nagen,997,0.20020288228988647,True,True\n125,doch will ich nicht verzagen,133,3,doch wil ich nicht verzagen,997,0.009252052754163742,True,True\n129,gedencken will ich an deinen tod,133,4,ge denckn wil ich an deinen tod,997,0.12208258360624313,True,True\n133,von welcher man sagen will,135,1,wer davon was wil sagen,1092,0.18671517074108124,False,True\n134,bey der welt und ihren kindern,138,1,bey der welt und ihren kindern,385,2.0015377701597392e-13,False,True\n135,gute freunde die mein lachen,138,6,gute freunde die mein lachen,385,1.9246374784696874e-13,False,True\n136,verläßt mich welt freund,142,0,verläkt mich welt freund,832,0.14260675013065338,True,True\n137,haab und guth und was sonst ist auf erden,142,1,haab und gut und was sonst ist auf erden,832,0.22123825550079346,True,True\n138,so glaub ich doch mit frohen muth,142,2,so glaub ich doch mit freyem muth,832,0.2647116780281067,True,True\n139,von gott soll mir hülf werden,142,3,von gott soll mir hülff werden,832,0.006873860023915768,True,True\n140,er will uns weder hier noch dort verlassen,142,4,er wil uns weder hier noch dort verlassen,832,0.012544594705104828,True,True\n141,wie er uns in wort,142,5,wie er uns im wort,832,0.08314214646816254,True,True\n142,durch seinen lieben sohn verspricht,142,6,durch seinen lieben sohn,832,0.27502909302711487,True,True\n147,bald sind wir frölich,143,7,wir sind gar bald verlohren,731,0.1742182970046997,False,True\n148,jesus trägt euch meine glieder,145,1,jesus euch meine glieder,591,0.19584128260612488,True,True\n149,sterbt ihr christus ruf euch wieder,145,3,christus rufft euch wieder,591,0.1945522129535675,True,True\n150,wenn die letzt’ trompet erklingt,145,4,wann die lekte trompt erklingt,591,0.2305760383605957,True,True\n151,die auch durch die gräber dringt,145,5,die auch durch die graber dringt,591,0.08978944271802902,True,True\n157,alles was mensch ist und heist,148,2,ja alles was mensch ist und heift,396,0.1895236074924469,True,True\n159,dir ewig treu zu bleiben,148,4,dir ewig treu zu bleiben,396,2.0797059007652413e-13,True,True\n163,du süsse lieb schenck uns deine gunst,150,0,du fusse lieb schenck uns deine gunst,612,0.08059239387512207,False,True\n167,lebendiger wind stiller aller schmerzen,152,1,lebendiger wind stiller aller schmer hen,615,0.1292925924062729,False,True\n169,mein lebetag will ich dich aus meinem sinn nicht lassen,156,0,mein lebetage wil ich dich aus meinem sinn nicht lassen,478,0.0947699174284935,True,True\n170,dich will ich stets,156,1,dich wil ich stets,478,0.008476141840219498,True,True\n173,gleich wie du mich,156,2,gleich wie du mich,478,2.0744820791729346e-13,True,True\n175,mein höchster ruhm hiemit zu deinem eigenthum beständiglich verschreiben,156,8,mein höchster ruhm hiemit zu deinem eigenthum be standiglich verschreiben,478,0.03677641972899437,True,True\n180,wenn wir nur daran gläuben,163,23,wann wir nur gebohren werden,1014,0.16924458742141724,False,True\n190,herr christ dein’ güt wir preisen,166,0,herr christ dein gut wir preisen,454,0.1067676693201065,True,True\n191,mit danck wir rühmen dich,166,1,mit danck wir rühmen dich,454,2.3281444589025313e-13,True,True\n193,hilf daß wir mit den weisen dir opfern williglich,166,2,hilff daß wir mit den weisen dir opffern williglich,454,0.04499749466776848,True,True\n194,und leben nach gebühr,166,3,und leben nach gebühr,454,5.488717119694897e-13,True,True\n195,so wird uns wohl gelingen,166,4,so wirds uns wol gelingen,454,0.130888432264328,True,True\n197,daß wir dort ewig singen,166,5,daß wir dort ewig fingen,454,0.19804221391677856,True,True\n199,herr gott dich loben wir,166,6,herr gott dich loben wir,454,6.076573706020882e-14,True,True\n"], ["E000061", 1368, "Predigt,Paragraph,Satz,Liedvers,Liederbuch,Ähnlichkeit,Validated,Dopplung\n6,ja was noch mehr,7,27,ja das noch mehr,789,0.1307857781648636,False,True\n41,sünde welt tod teufel und hölle,31,16,welt tod teuffel sünd und hölle,1014,0.16633275151252747,False,True\n53,den wil er nicht verlassen,36,3,den wird er nicht verlassen,771,0.17462410032749176,False,True\n69,da wir noch seine feinde waren,41,26,da wir noch feinde waren,794,0.16950231790542603,False,True\n81,schickt das hertze da hinein,43,0,schickt das hertze dahinein,591,0.18946918845176697,False,True\n87,wann dort herr jesu,48,0,wann dort herr jesu,473,3.792129370933095e-13,True,True\n88,da will ich dir,48,3,da wil ich dir,473,0.147068053483963,True,True\n92,wann alles wird wol klingen,48,4,wann alles wird wol klingen,473,2.061949650735903e-13,True,True\n94,lob und danck singen,48,5,lob und danck singen,473,7.823061453195515e-14,True,True\n96,mit ihrer macht und gewalt,49,41,durch dein macht und gewalt,463,0.1535627692937851,False,False\n115,herr gott dich loben wir,72,0,herr gott dich loben wir,969,6.076573706020882e-14,False,True\n133,die du mir aufgebunden hast,84,48,die ihr habt an mir gebracht,1040,0.17422764003276825,False,True\n"], ["E000072", 1348, "Predigt,Paragraph,Satz,Liedvers,Liederbuch,Ähnlichkeit,Validated,Dopplung\n14,lobt ihn mit hertz und munde,17,64,s lobt ihn mit herz und munde,900,0.1601807177066803,True,False\n15,welchs er uns beydes schenckt,17,65,welchs er uns bendes schenckt,900,0.1522902101278305,True,False\n16,sonst verdirbt alle zeit,17,68,sonst verdirbt alle zeit,900,6.809497085126515e-14,True,False\n19,den glauben mehr stärck den verstand,22,2,den glauben mehr stärck den verstand,608,2.5593359354557366e-13,True,False\n20,daß uns dein nahme werd wohl bekant,22,3,daß uns dein nam sey wol bekannt,608,0.2857702374458313,True,False\n25,das wasser das muß geben fisch,28,10,das wasser muß geben fisch,722,0.09079962223768234,False,True\n33,wenn es gieng nach des fleisches muth,41,28,wann es gieng nach des fleisches muth,792,0.041909102350473404,False,False\n48,himmlisch leben wird gott geben mir dort oben,55,70,eya eya himmlisch leben wird er geben mir dort oben,741,0.2218860685825348,True,False\n49,ewig soll so dann mein hertz ihn loben,55,71,ewig soll mein hertz ihn loben,741,0.11531767249107361,True,False\n53,breit aus die flügel beyde,61,3,breit aus die flugel beyde,114,0.14837898313999176,False,True\n54,gleich wie sich fein ein vögelein in hole bäum verstecket,61,12,gleich wie sich fein ein vogelein im holen baum verstecket,219,0.17370812594890594,True,False\n55,menschen und vieh erschrecket,61,14,menschen und vieh erschrecket,219,2.31507711221865e-13,True,False\n56,also herr christ mein zuflucht ist die höle deiner wunden,61,15,wfo herr christ mein zuflucht ist die hile deiner wunden,219,0.2202475666999817,True,False\n60,wenn wir nur daran glauben,64,36,wann wir ihm nur glauben,296,0.13356268405914307,False,True\n"], ["E000038", 1193, "Predigt,Paragraph,Satz,Liedvers,Liederbuch,Ähnlichkeit,Validated,Dopplung\n5,bis auf die zeiten,33,16,bis an die zeit,458,0.06635421514511108,False,False\n8,und das um soviel mehr,42,34,und zwar um so viels mehr,956,0.067165806889534,False,False\n15,da es noch heute heisset,58,2,weils heute heiffet noch,103,0.11192624270915985,False,False\n16,man soll o gott,59,14,man soll o gott,1111,2.738747813604836e-13,True,False\n17,mein ganzes herz ermuntre sich,59,16,mein ganzes herz ermuntre sich,1111,1.777376531543473e-13,True,True\n18,mein geist und leib erfreue dich,59,17,mein geist und leib erfreue dich,1111,6.81883342108433e-14,True,False\n22,gebt unserm gott die ehre,59,18,gebt unserm gott die ehre,1111,2.8752521197272785e-13,True,True\n24,ach gott wie manches herzeleid begegnet mir zu dieser zeit,61,15,gott wie manches herkeleid begegnet mir zu dieser zeit,863,0.10235755890607834,True,False\n25,der schmale weg ist trübsal voll,61,16,der schmale weg ist trübfalls voll,863,0.02876545675098896,True,True\n26,und das um soviel mehr,61,57,und zwar um so viels mehr,956,0.067165806889534,False,False\n32,hier zeitlich und dort ewiglich,63,20,hie und dort in ewigkeit,755,0.1280355155467987,False,True\n44,sey lob und ehr mit hohem preiß,79,0,sey lob und ehr mit hohem preiß,357,9.589744498711764e-14,False,False\n"], ["E000070", 1190, "Predigt,Paragraph,Satz,Liedvers,Liederbuch,Ähnlichkeit,Validated,Dopplung\n11,und was er zusaget,6,22,und was er fpricht,668,0.16002850234508514,False,True\n12,sey lob und ehr mit hohem preiß,7,4,sey lob und ehr mit hohem preiß,357,9.589744498711764e-14,False,True\n15,und solches um so viel desto mehr,13,0,und zwar um so viels mehr,956,0.12454398721456528,False,True\n40,damit seins vaters zorn gestillt,31,1,damit seins vaters zorn geftillt,356,0.17849375307559967,False,False\n41,der über uns gieng alle,31,2,der über uns gieng alle,356,5.2416404550115203e-14,False,False\n46,da wird durchaus nichts anders daraus,38,5,da wird nun nichts anders draus,754,0.19001972675323486,False,True\n47,werd ich im grab nicht bleiben,40,1,werd ich im grab nicht bleiben,997,2.0505653923995337e-13,True,True\n48,mein höchster trost dein auffarth ist,40,2,mein höchster trost dein aufs fahrt ist,997,0.15773393213748932,True,True\n49,todsfurcht kan sie vertreiben,40,3,todsfurcht kan sie vertreiben,997,3.9928097720492994e-13,True,True\n50,denn wo du bist da komm ich hin,40,4,denn wodu bist da komm ich hin,997,0.16326995193958282,True,True\n51,daß ich stets bey dir leb und bin,40,5,daß ich stets bey dir leb und bin,997,2.2504742481447432e-13,True,True\n52,drum fahr ich hin mit freuden,40,6,drum fahr ich hin mit freuden,997,4.1573813619119604e-13,True,False\n56,ein ewges leben hast du mir mit deinem tod erworben,43,1,ein ewges leben hast mir mit dei nem tod erworben,997,0.15171119570732117,False,True\n59,ob mich der tod nimmt hin,43,4,ob mich der tod nimmt hin,1007,6.611481110849193e-14,True,True\n62,ist sterben mein gewinn,43,5,sterben ist ist mein gewinn,1008,0.12634290754795074,True,True\n64,und christus ist mein leben,43,6,und christus ist mein leben,1007,4.3830600769938916e-14,True,True\n66,dem thu ich mich ergeben,43,7,dem thu ich mich ergeben,1007,3.986586993680319e-13,True,True\n69,ich sterb gleich heut oder morgen,43,8,ich sterb heut oder morgen,1007,0.036770254373550415,True,False\n70,mein seel wird er versorgen,43,9,mein seel wird er versorgen,1007,5.957214566478311e-14,True,True\n74,das ist mein trost,44,0,es ist mein segen,101,0.163375586271286,True,True\n78,das ist mein trost,44,7,es ist mein segen,101,0.163375586271286,True,True\n82,das ist mein trost,44,14,es ist mein segen,101,0.163375586271286,True,True\n84,leben und seeligkeit,44,23,die warheit und das leben,403,0.17303526401519775,False,True\n85,das ist mein trost zu allerzeit,45,0,das ist mein trost zu aller zeit,1003,0.008926699869334698,True,True\n86,in allem creutz und traurigkeit,45,1,jn allem creuß und traurigkeit,1003,0.12739551067352295,True,True\n88,ich weiß das ich am jüngsten tag,45,2,ich weiß daß ich am jungsten tag,1003,0.18039968609809875,True,True\n89,ohn alle klag werd auferstehen aus meinem grab,45,3,ohn alle klag werd aufferstehn aus meinem grab,1003,0.04843384772539139,True,True\n98,weil gottes zorn anbricht,60,6,weil gottes zorn entglommen,204,0.0913110077381134,False,True\n105,aus tieffer noth schrey ich zu dir,65,11,mel aus tieffer noth schrey ich zu dir,910,0.11507423967123032,False,True\n111,die welt erzittert ob dem tod,67,11,die welt erzittert ob den tod,791,0.01861063949763775,False,True\n119,mit säiten und pfeiffen,69,7,mit spiessen und mit stangen,501,0.1819237321615219,False,True\n131,gott will ich lassen rathen,77,0,gott wil ich lassen rathen,44,0.010178809054195881,True,True\n132,er segne meine thaten,77,2,er segne meine thaten,44,7.909722410468639e-14,True,True\n133,mein fürnehmen und sach,77,3,mein fürnehmen und sach,44,6.358898596483392e-14,True,True\n137,mein leib mein seel,77,5,mein seel mein leib,44,0.03694099932909012,True,True\n140,er machs wies ihm gefällt,77,7,er machs wies ihm gefällt,44,2.320858891353972e-13,True,True\n145,danckt dem herren groß ist der könig der ehren,80,3,danckt dem herren groß ist der könig der ehren,741,2.5965866826474504e-13,False,True\n"]]}